gassist_text/__init__.py
gassist_text/assistant_helpers.py
gassist_text/py.typed
gassist_text/textinput.py
gassist_text-0.0.14.dist-info/licenses/LICENSE
google/assistant/embedded/v1alpha2/__init__.py
google/assistant/embedded/v1alpha2/embedded_assistant_pb2.py
google/assistant/embedded/v1alpha2/embedded_assistant_pb2_grpc.py
gassist_text-0.0.14.dist-info/METADATA
gassist_text-0.0.14.dist-info/WHEEL
gassist_text-0.0.14.dist-info/top_level.txt
gassist_text-0.0.14.dist-info/RECORD
