Metadata-Version: 2.4
Name: gassist-text
Version: 0.0.14
Summary: A Python library for interacting with Google Assistant API via text
Author-email: tronikos <tronikos@gmail.com>
License-Expression: Apache-2.0
Project-URL: Homepage, https://github.com/tronikos/gassist_text
Project-URL: Bug Tracker, https://github.com/tronikos/gassist_text/issues
Requires-Python: >=3.11
License-File: LICENSE
Requires-Dist: google-auth>=0.3.0
Requires-Dist: grpcio>=1.48.0
Requires-Dist: protobuf>=3.20.0
Requires-Dist: requests>=2.20.0
Dynamic: license-file
